magic_di/__init__.py
magic_di/_connectable.py
magic_di/_container.py
magic_di/_injector.py
magic_di/_signature.py
magic_di/_utils.py
magic_di/celery/__init__.py
magic_di/celery/_async_utils.py
magic_di/celery/_loader.py
magic_di/celery/_provide.py
magic_di/celery/_task.py
magic_di/exceptions.py
magic_di/fastapi/__init__.py
magic_di/fastapi/_app.py
magic_di/fastapi/_provide.py
magic_di/healthcheck.py
magic_di/py.typed
magic_di/testing.py
magic_di/utils.py
magic_di-0.3.0.dist-info/LICENSE
magic_di-0.3.0.dist-info/METADATA
magic_di-0.3.0.dist-info/WHEEL
magic_di-0.3.0.dist-info/RECORD
