Metadata-Version: 2.1
Name: magic-di
Version: 0.3.0
Summary: Dependency Injector that makes your life easier with built-in support of FastAPI, Celery (but it can be integrated with everything)
Home-page: https://woltapp.github.io/magic-di
License: MIT
Author: Nikita Zavadin
Author-email: nikita.zavadin@wolt.com
Requires-Python: >=3.10,<4.0
Classifier: Development Status :: 4 - Beta
Classifier: Intended Audience :: Developers
Classifier: License :: OSI Approved :: MIT License
Classifier: Operating System :: OS Independent
Classifier: Programming Language :: Python
Classifier: Programming Language :: Python :: 3
Classifier: Programming Language :: Python :: 3.10
Classifier: Programming Language :: Python :: 3.11
Classifier: Programming Language :: Python :: 3.12
Classifier: Programming Language :: Python :: 3.13
Classifier: Topic :: Software Development :: Libraries :: Python Modules
Classifier: Typing :: Typed
Provides-Extra: celery
Provides-Extra: fastapi
Requires-Dist: celery (>=5,<6) ; extra == "celery"
Requires-Dist: fastapi ; extra == "fastapi"
Project-URL: Documentation, https://woltapp.github.io/magic-di
Project-URL: Repository, https://github.com/woltapp/magic-di
